CHANGELOG.rst
LICENSE.txt
MANIFEST.in
README.rst
requirements.txt
setup.cfg
setup.py
scine_heron/__init__.py
scine_heron/__main__.py
scine_heron/_version.py
scine_heron/central_widget.py
scine_heron/config.py
scine_heron/main_window.py
scine_heron/molecular_viewer.py
scine_heron/multithread.py
scine_heron/status_manager.py
scine_heron/utilities.py
scine_heron.egg-info/PKG-INFO
scine_heron.egg-info/SOURCES.txt
scine_heron.egg-info/dependency_links.txt
scine_heron.egg-info/entry_points.txt
scine_heron.egg-info/not-zip-safe
scine_heron.egg-info/requires.txt
scine_heron.egg-info/top_level.txt
scine_heron/autocas/__init__.py
scine_heron/autocas/autocas_controller.py
scine_heron/autocas/autocas_project_widget.py
scine_heron/autocas/autocas_settings.py
scine_heron/autocas/autocas_widget.py
scine_heron/autocas/autocas_wrapper.py
scine_heron/autocas/basic_options.py
scine_heron/autocas/entanglement_diagram.py
scine_heron/autocas/file_tree_widget.py
scine_heron/autocas/mo_diagram.py
scine_heron/autocas/open_molcas_popup.py
scine_heron/autocas/options.py
scine_heron/autocas/options_bck.py
scine_heron/autocas/options_status_manager.py
scine_heron/autocas/orbital_options_widget.py
scine_heron/autocas/orbital_viewer_widget.py
scine_heron/autocas/output_widget.py
scine_heron/autocas/result_widget.py
scine_heron/autocas/signal_handler.py
scine_heron/autocas/toolbar_widget.py
scine_heron/calculators/__init__.py
scine_heron/calculators/calculator.py
scine_heron/calculators/create_calculator_widget.py
scine_heron/calculators/hybrid_model_construction.py
scine_heron/chemoton/__init__.py
scine_heron/chemoton/chemoton_widget.py
scine_heron/chemoton/chemoton_widget_container.py
scine_heron/chemoton/class_searcher.py
scine_heron/chemoton/class_selection_widget.py
scine_heron/chemoton/create_chemoton_widget.py
scine_heron/chemoton/energy_reference_builder.py
scine_heron/chemoton/filter_builder.py
scine_heron/chemoton/gear_options_widget.py
scine_heron/chemoton/grouped_combo_box.py
scine_heron/chemoton/model_combination_builder.py
scine_heron/chemoton/reference_state_builder.py
scine_heron/chemoton/rule_builder.py
scine_heron/chemoton/side_builder.py
scine_heron/chemoton/uncertainty_estimator_builder.py
