Metadata-Version: 2.1
Name: scine-heron
Version: 2.0.0
Summary: Graphical user interface for SCINE
Home-page: https://www.scine.ethz.ch
Author: ETH Zurich, Department of Chemistry and Applied Biosciences, Reiher Group
Author-email: scine@phys.chem.ethz.ch
License: BSD (3-clause)
Platform: UNKNOWN
Classifier: Programming Language :: Python
Classifier: Programming Language :: C++
Classifier: Development Status :: 5 - Production/Stable
Classifier: Intended Audience :: Science/Research
Classifier: License :: OSI Approved :: BSD License
Classifier: Natural Language :: English
Classifier: Topic :: Scientific/Engineering :: Chemistry
Requires-Python: >=3.6
Provides-Extra: all
Provides-Extra: autocas_chemoton_database_molassembler_serenity_xtb
Provides-Extra: autocas_chemoton_molassembler_serenity_swoose_xtb
Provides-Extra: chemoton_database_molassembler_serenity_swoose_xtb
Provides-Extra: autocas_chemoton_database_molassembler_serenity_swoose
Provides-Extra: autocas_chemoton_database_serenity_swoose_xtb
Provides-Extra: autocas_database_molassembler_serenity_swoose_xtb
Provides-Extra: autocas_chemoton_database_molassembler_swoose_xtb
Provides-Extra: autocas_chemoton_molassembler_serenity_xtb
Provides-Extra: chemoton_database_molassembler_serenity_xtb
Provides-Extra: chemoton_molassembler_serenity_swoose_xtb
Provides-Extra: autocas_chemoton_database_molassembler_serenity
Provides-Extra: autocas_chemoton_molassembler_serenity_swoose
Provides-Extra: chemoton_database_molassembler_serenity_swoose
Provides-Extra: autocas_chemoton_database_serenity_xtb
Provides-Extra: autocas_chemoton_serenity_swoose_xtb
Provides-Extra: chemoton_database_serenity_swoose_xtb
Provides-Extra: autocas_chemoton_database_serenity_swoose
Provides-Extra: autocas_database_molassembler_serenity_xtb
Provides-Extra: autocas_molassembler_serenity_swoose_xtb
Provides-Extra: database_molassembler_serenity_swoose_xtb
Provides-Extra: autocas_database_molassembler_serenity_swoose
Provides-Extra: autocas_database_serenity_swoose_xtb
Provides-Extra: autocas_chemoton_database_molassembler_xtb
Provides-Extra: autocas_chemoton_molassembler_swoose_xtb
Provides-Extra: chemoton_database_molassembler_swoose_xtb
Provides-Extra: autocas_chemoton_database_molassembler_swoose
Provides-Extra: autocas_chemoton_database_swoose_xtb
Provides-Extra: autocas_database_molassembler_swoose_xtb
Provides-Extra: chemoton_molassembler_serenity_xtb
Provides-Extra: autocas_chemoton_molassembler_serenity
Provides-Extra: chemoton_database_molassembler_serenity
Provides-Extra: chemoton_molassembler_serenity_swoose
Provides-Extra: autocas_chemoton_serenity_xtb
Provides-Extra: chemoton_database_serenity_xtb
Provides-Extra: chemoton_serenity_swoose_xtb
Provides-Extra: autocas_chemoton_database_serenity
Provides-Extra: autocas_chemoton_serenity_swoose
Provides-Extra: chemoton_database_serenity_swoose
Provides-Extra: autocas_molassembler_serenity_xtb
Provides-Extra: database_molassembler_serenity_xtb
Provides-Extra: molassembler_serenity_swoose_xtb
Provides-Extra: autocas_database_molassembler_serenity
Provides-Extra: autocas_molassembler_serenity_swoose
Provides-Extra: database_molassembler_serenity_swoose
Provides-Extra: autocas_database_serenity_xtb
Provides-Extra: autocas_serenity_swoose_xtb
Provides-Extra: database_serenity_swoose_xtb
Provides-Extra: autocas_database_serenity_swoose
Provides-Extra: autocas_chemoton_molassembler_xtb
Provides-Extra: chemoton_database_molassembler_xtb
Provides-Extra: chemoton_molassembler_swoose_xtb
Provides-Extra: autocas_chemoton_database_molassembler
Provides-Extra: autocas_chemoton_molassembler_swoose
Provides-Extra: chemoton_database_molassembler_swoose
Provides-Extra: autocas_chemoton_database_xtb
Provides-Extra: autocas_chemoton_swoose_xtb
Provides-Extra: chemoton_database_swoose_xtb
Provides-Extra: autocas_chemoton_database_swoose
Provides-Extra: autocas_database_molassembler_xtb
Provides-Extra: autocas_molassembler_swoose_xtb
Provides-Extra: database_molassembler_swoose_xtb
Provides-Extra: autocas_database_molassembler_swoose
Provides-Extra: autocas_database_swoose_xtb
Provides-Extra: chemoton_molassembler_serenity
Provides-Extra: chemoton_serenity_xtb
Provides-Extra: autocas_chemoton_serenity
Provides-Extra: chemoton_database_serenity
Provides-Extra: chemoton_serenity_swoose
Provides-Extra: molassembler_serenity_xtb
Provides-Extra: autocas_molassembler_serenity
Provides-Extra: database_molassembler_serenity
Provides-Extra: molassembler_serenity_swoose
Provides-Extra: autocas_serenity_xtb
Provides-Extra: database_serenity_xtb
Provides-Extra: serenity_swoose_xtb
Provides-Extra: autocas_database_serenity
Provides-Extra: autocas_serenity_swoose
Provides-Extra: database_serenity_swoose
Provides-Extra: chemoton_molassembler_xtb
Provides-Extra: autocas_chemoton_molassembler
Provides-Extra: chemoton_database_molassembler
Provides-Extra: chemoton_molassembler_swoose
Provides-Extra: autocas_chemoton_xtb
Provides-Extra: chemoton_database_xtb
Provides-Extra: chemoton_swoose_xtb
Provides-Extra: autocas_chemoton_database
Provides-Extra: autocas_chemoton_swoose
Provides-Extra: chemoton_database_swoose
Provides-Extra: autocas_molassembler_xtb
Provides-Extra: database_molassembler_xtb
Provides-Extra: molassembler_swoose_xtb
Provides-Extra: autocas_database_molassembler
Provides-Extra: autocas_molassembler_swoose
Provides-Extra: database_molassembler_swoose
Provides-Extra: autocas_database_xtb
Provides-Extra: autocas_swoose_xtb
Provides-Extra: database_swoose_xtb
Provides-Extra: autocas_database_swoose
Provides-Extra: chemoton_serenity
Provides-Extra: molassembler_serenity
Provides-Extra: serenity_xtb
Provides-Extra: autocas_serenity
Provides-Extra: database_serenity
Provides-Extra: serenity_swoose
Provides-Extra: chemoton_molassembler
Provides-Extra: chemoton_xtb
Provides-Extra: autocas_chemoton
Provides-Extra: chemoton_database
Provides-Extra: chemoton_swoose
Provides-Extra: molassembler_xtb
Provides-Extra: autocas_molassembler
Provides-Extra: database_molassembler
Provides-Extra: molassembler_swoose
Provides-Extra: autocas_xtb
Provides-Extra: database_xtb
Provides-Extra: swoose_xtb
Provides-Extra: autocas_database
Provides-Extra: autocas_swoose
Provides-Extra: database_swoose
Provides-Extra: serenity
Provides-Extra: chemoton
Provides-Extra: molassembler
Provides-Extra: xtb
Provides-Extra: autocas
Provides-Extra: database
Provides-Extra: swoose
